pyfileext
